barotropic/__init__.py
barotropic/constants.py
barotropic/diagnostics.py
barotropic/formatting.py
barotropic/grid.py
barotropic/init.py
barotropic/io.py
barotropic/model.py
barotropic/plot.py
barotropic/rhs.py
barotropic/state.py
barotropic-3.1.0.dist-info/LICENSE
barotropic-3.1.0.dist-info/METADATA
barotropic-3.1.0.dist-info/WHEEL
barotropic-3.1.0.dist-info/top_level.txt
barotropic-3.1.0.dist-info/RECORD
