Metadata-Version: 2.1
Name: barotropic
Version: 3.1.0
Summary: A framework for barotropic analysis and modelling of the atmosphere
Author-email: Christopher Polster <chpolste@tuta.io>
License: 
Project-URL: documentation, https://chpolste.github.io/barotropic
Project-URL: source, https://github.com/chpolste/barotropic
Classifier: License :: OSI Approved :: Apache Software License
Classifier: Programming Language :: Python :: 3
Classifier: Programming Language :: Python :: 3 :: Only
Classifier: Intended Audience :: Science/Research
Classifier: Topic :: Scientific/Engineering :: Atmospheric Science
Requires-Python: >=3.9
License-File: LICENSE
Requires-Dist: numpy >=1.20.3
Requires-Dist: scipy >=1.6.3
Requires-Dist: pyspharm >=1.0.9
Provides-Extra: docs
Requires-Dist: Sphinx >=7.3.7 ; extra == 'docs'
Requires-Dist: nbsphinx >=0.9.4 ; extra == 'docs'
Provides-Extra: extras
Requires-Dist: matplotlib >=3.4.2 ; extra == 'extras'
Requires-Dist: PyWavelets >=1.1.1 ; extra == 'extras'
Requires-Dist: falwa >=1.0.0 ; extra == 'extras'
Requires-Dist: xarray >=2022.03.0 ; extra == 'extras'
Provides-Extra: test
Requires-Dist: pytest >=7 ; extra == 'test'
